{
  "totalArticles": 33,
  "totalCategories": 10,
  "estimatedContributors": 3,
  "totalTags": 75,
  "categories": [
    {
      "name": "Agri-Basics",
      "count": 2
    },
    {
      "name": "Crop-Production",
      "count": 4
    },
    {
      "name": "Agri-Marketing",
      "count": 3
    },
    {
      "name": "Farm-Management",
      "count": 5
    },
    {
      "name": "Agri-Advanced",
      "count": 3
    },
    {
      "name": "Facility-Farming",
      "count": 3
    },
    {
      "name": "Livestock-Health",
      "count": 1
    },
    {
      "name": "Field-Visits",
      "count": 5
    },
    {
      "name": "Smart-Farming",
      "count": 5
    },
    {
      "name": "Grants-Planning",
      "count": 2
    }
  ],
  "topTags": [
    {
      "name": "國本學堂",
      "count": 33
    },
    {
      "name": "第三屆",
      "count": 8
    },
    {
      "name": "第五屆",
      "count": 4
    },
    {
      "name": "場域交流",
      "count": 4
    },
    {
      "name": "第四屆",
      "count": 4
    },
    {
      "name": "卓越班",
      "count": 3
    },
    {
      "name": "溫室",
      "count": 3
    },
    {
      "name": "智慧農業",
      "count": 3
    },
    {
      "name": "農業基礎",
      "count": 2
    },
    {
      "name": "作物生產",
      "count": 2
    },
    {
      "name": "小番茄",
      "count": 2
    },
    {
      "name": "農產品銷售",
      "count": 2
    },
    {
      "name": "小黃瓜",
      "count": 2
    },
    {
      "name": "農業進階",
      "count": 2
    },
    {
      "name": "家禽",
      "count": 2
    },
    {
      "name": "設施農業",
      "count": 2
    },
    {
      "name": "農場管理",
      "count": 2
    },
    {
      "name": "土壤學",
      "count": 1
    },
    {
      "name": "設施蔬果",
      "count": 1
    },
    {
      "name": "通路策略",
      "count": 1
    }
  ],
  "languageDistribution": {
    "zh-TW": 33,
    "en": 0
  },
  "lastUpdated": "2026-04-18T07:49:38.823Z"
}